docs/source/conf.py
konrad/__init__.py
konrad/atmosphere.py
konrad/cloud.py
konrad/cloudoptics.py
konrad/component.py
konrad/constants.py
konrad/convection.py
konrad/core.py
konrad/entrainment.py
konrad/lapserate.py
konrad/netcdf.py
konrad/ozone.py
konrad/physics.py
konrad/surface.py
konrad/upwelling.py
konrad/utils.py
konrad/data/Cariolle_data.nc
konrad/data/ECHAM6_CldOptProps.nc
konrad/humidity/__init__.py
konrad/humidity/relative_humidity.py
konrad/humidity/stratosphere.py
konrad/radiation/__init__.py
konrad/radiation/arts.py
konrad/radiation/common.py
konrad/radiation/radiation.py
konrad/radiation/rrtmg.py
konrad/test/__init__.py
konrad/test/test_atmosphere.py
konrad/test/test_convection.py
konrad/test/test_rce.py
konrad/test/test_relative-humidity.py
konrad/test/reference_data/reference.nc
konrad-1.0.2.dist-info/LICENSE
konrad-1.0.2.dist-info/METADATA
konrad-1.0.2.dist-info/WHEEL
konrad-1.0.2.dist-info/top_level.txt
konrad-1.0.2.dist-info/RECORD
