Metadata-Version: 2.1
Name: konrad
Version: 1.0.2
Summary: 'Implementation of a radiative-convective equilibrium model.
Home-page: https://github.com/atmtools/konrad
Author: The konrad developers
License: MIT
Classifier: Intended Audience :: Science/Research
Classifier: License :: OSI Approved :: MIT License
Classifier: Programming Language :: Python :: 3.8
Classifier: Programming Language :: Python :: 3.9
Classifier: Programming Language :: Python :: 3.10
Requires-Python: >=3.8
License-File: LICENSE
Requires-Dist: matplotlib (>=2.0.0)
Requires-Dist: netcdf4 (>=1.2.7)
Requires-Dist: numpy (>1.22.0)
Requires-Dist: scipy (>=0.19.0)
Requires-Dist: typhon (>=0.7.0)
Requires-Dist: xarray (>=0.9.1)
Requires-Dist: climt (>=0.16.25)
Requires-Dist: sympl (>=0.4.0)
Provides-Extra: arts
Requires-Dist: pyarts ; extra == 'arts'
Provides-Extra: docs
Requires-Dist: jupyter-book ; extra == 'docs'
Requires-Dist: sphinx ; extra == 'docs'
Requires-Dist: sphinx-rtd-theme ; extra == 'docs'
Provides-Extra: tests
Requires-Dist: pytest ; extra == 'tests'
